cpz/__init__.py
cpz/cli.py
cpz/py.typed
cpz/clients/__init__.py
cpz/clients/async_.py
cpz/clients/base.py
cpz/clients/sync.py
cpz/common/__init__.py
cpz/common/auth.py
cpz/common/backoff.py
cpz/common/config.py
cpz/common/cpz_ai.py
cpz/common/display.py
cpz/common/enums.py
cpz/common/errors.py
cpz/common/logging.py
cpz/common/models.py
cpz/common/pagination.py
cpz/common/rate_limit.py
cpz/common/utils.py
cpz/data/__init__.py
cpz/data/client.py
cpz/data/interfaces.py
cpz/data/models.py
cpz/data/providers/__init__.py
cpz/data/providers/alpaca.py
cpz/data/providers/alphavantage.py
cpz/data/providers/databento.py
cpz/data/providers/edgar.py
cpz/data/providers/fred.py
cpz/data/providers/polygon.py
cpz/data/providers/social.py
cpz/data/providers/twelve.py
cpz/data/providers/yfinance.py
cpz/execution/__init__.py
cpz/execution/cpz_native_adapter.py
cpz/execution/enums.py
cpz/execution/interfaces.py
cpz/execution/models.py
cpz/execution/router.py
cpz/execution/smoke_test.py
cpz/execution/alpaca/__init__.py
cpz/execution/alpaca/adapter.py
cpz/execution/alpaca/mapping.py
cpz/execution/alpaca/stream.py
cpz_ai-1.6.0.dist-info/METADATA
cpz_ai-1.6.0.dist-info/WHEEL
cpz_ai-1.6.0.dist-info/entry_points.txt
cpz_ai-1.6.0.dist-info/top_level.txt
cpz_ai-1.6.0.dist-info/RECORD
