Metadata-Version: 2.4
Name: cpz-ai
Version: 1.6.0
Summary: CPZAI Python SDK for trading strategies, market data, and multi-broker execution
Author-email: CPZAI <contact@cpz-lab.com>
Project-URL: Homepage, https://www.cpz-lab.com/cpz-ai
Project-URL: Repository, https://github.com/CPZ-Lab/cpz-py
Classifier: Programming Language :: Python :: 3
Classifier: Programming Language :: Python :: 3 :: Only
Classifier: Programming Language :: Python :: 3.9
Classifier: Programming Language :: Python :: 3.10
Classifier: Programming Language :: Python :: 3.11
Classifier: Programming Language :: Python :: 3.12
Classifier: Typing :: Typed
Classifier: Development Status :: 3 - Alpha
Classifier: Intended Audience :: Developers
Classifier: License :: Other/Proprietary License
Requires-Python: >=3.9
Requires-Dist: pydantic<3,>=2.6
Requires-Dist: requests<3,>=2.31
Requires-Dist: httpx<0.28,>=0.25
Requires-Dist: alpaca-py>=0.21
Requires-Dist: structlog<25,>=24
Requires-Dist: click<9,>=8.1
Requires-Dist: python-dotenv<2,>=1.0
Requires-Dist: pytz
Provides-Extra: dev
Requires-Dist: pytest; extra == "dev"
Requires-Dist: pytest-cov; extra == "dev"
Requires-Dist: mypy; extra == "dev"
Requires-Dist: ruff; extra == "dev"
Requires-Dist: black; extra == "dev"
Requires-Dist: isort; extra == "dev"
Requires-Dist: types-requests; extra == "dev"
Requires-Dist: pre-commit; extra == "dev"
Provides-Extra: yfinance
Requires-Dist: yfinance>=0.2; extra == "yfinance"
Provides-Extra: databento
Requires-Dist: databento>=0.40; extra == "databento"
Provides-Extra: all
Requires-Dist: databento>=0.40; extra == "all"
Requires-Dist: yfinance>=0.2; extra == "all"
